lorem.py
test_lorem.py
python_lorem-1.3.0.post3.dist-info/LICENSE
python_lorem-1.3.0.post3.dist-info/METADATA
python_lorem-1.3.0.post3.dist-info/WHEEL
python_lorem-1.3.0.post3.dist-info/top_level.txt
python_lorem-1.3.0.post3.dist-info/zip-safe
python_lorem-1.3.0.post3.dist-info/RECORD
