Metadata-Version: 2.1
Name: python-lorem
Version: 1.3.0.post3
Summary: Lorem ipsum generator.
Author-email: Jarry Shaw <jarryshaw@icloud.com>
Maintainer: Jarry Shaw
License: BSD 3-Clause License
Project-URL: homepage, https://jarryshaw.github.io/lorem/
Project-URL: documentation, https://jarryshaw.github.io/lorem/
Project-URL: repository, https://github.com/JarryShaw/lorem
Project-URL: changelog, https://github.com/JarryShaw/lorem/releases
Keywords: lorem,loremipsum
Classifier: Development Status :: 5 - Production/Stable
Classifier: Intended Audience :: Developers
Classifier: License :: OSI Approved :: BSD License
Classifier: Natural Language :: English
Classifier: Operating System :: OS Independent
Classifier: Programming Language :: Python
Classifier: Programming Language :: Python :: 3.5
Classifier: Programming Language :: Python :: 3.6
Classifier: Programming Language :: Python :: 3.7
Classifier: Programming Language :: Python :: 3.8
Classifier: Programming Language :: Python :: 3 :: Only
Classifier: Topic :: Software Development
Classifier: Topic :: Utilities
Classifier: Typing :: Typed
Requires-Python: >=3.5
License-File: LICENSE
Requires-Dist: typing-extensions; python_version < "3.8"
Provides-Extra: docs
Requires-Dist: Sphinx>=6.1.3; extra == "docs"
Requires-Dist: sphinx-autodoc-typehints; extra == "docs"
Requires-Dist: sphinx-opengraph; extra == "docs"
Requires-Dist: sphinx-copybutton; extra == "docs"
Requires-Dist: furo; extra == "docs"
